[
  {
    "title": "Anatomy Quick Tips: Skin",
    "url": "https://youtube.com/watch?v=V_E1ARR_AAg",
    "duration": 1244.0,
    "views": 1969444,
    "uploader": "Sinix Design"
  },
  {
    "title": "The Secret “Chinese Youtube” Taught Me How to Actually Paint Skin.",
    "url": "https://youtube.com/watch?v=LwGZjkADSQk",
    "duration": 799.0,
    "views": 121002,
    "uploader": "Kraymer Art"
  },
  {
    "title": "Painting Skin Tones",
    "url": "https://youtube.com/watch?v=mi62WC9LqZA",
    "duration": 1224.0,
    "views": 1601078,
    "uploader": "Proko"
  },
  {
    "title": "How to color and render skin",
    "url": "https://youtube.com/watch?v=Am7WVUoCFKw",
    "duration": 821.0,
    "views": 589279,
    "uploader": "Bluebiscuits"
  },
  {
    "title": "HOW I PAINT SKIN/LIGHT",
    "url": "https://youtube.com/watch?v=dZNz3WlB-7M",
    "duration": 853.0,
    "views": 845514,
    "uploader": "NIRO"
  },
  {
    "title": "How To Paint Skin - Digital Painting Tutorial!",
    "url": "https://youtube.com/watch?v=hvrbG6X0rDI",
    "duration": 922.0,
    "views": 385011,
    "uploader": "Ross Draws"
  },
  {
    "title": "How I COLOR and RENDER SKIN in IBISPAINT X",
    "url": "https://youtube.com/watch?v=QVd1gHx3OZo",
    "duration": 862.0,
    "views": 66501,
    "uploader": "Fungzau"
  },
  {
    "title": "How To Paint Skin That Doesn't Suck",
    "url": "https://youtube.com/watch?v=sh9tSJX2Hq0",
    "duration": 547.0,
    "views": 272142,
    "uploader": "Digital Magician"
  },
  {
    "title": "Skin Shading Tutorial (Digital Painting)",
    "url": "https://youtube.com/watch?v=Ap4mfIA4UEY",
    "duration": 1229.0,
    "views": 413149,
    "uploader": "ericanthonyj"
  },
  {
    "title": "This 1 Minute Digital Painting Tutorial will Teach you More Than You Expect",
    "url": "https://youtube.com/watch?v=KwvsP5Vgbjg",
    "duration": 118.0,
    "views": 785914,
    "uploader": "Mohammed Agbadi"
  }
]