[
  {
    "title": "LLOUD Official",
    "url": "https://youtube.com/watch?v=UC6-BgjsBa5R3PZQ_kZ8hKPg",
    "duration": 0,
    "views": 0,
    "uploader": "LLOUD Official"
  },
  {
    "title": "LISA - 'MONEY' EXCLUSIVE PERFORMANCE VIDEO",
    "url": "https://youtube.com/watch?v=dNCWe_6HAM8",
    "duration": 171.0,
    "views": 1208237390,
    "uploader": "BLACKPINK"
  },
  {
    "title": "Anyma, LISA - Bad Angel (Official Music Video)",
    "url": "https://youtube.com/watch?v=dKmPEhJ4wjY",
    "duration": 150.0,
    "views": 16579090,
    "uploader": "Anyma and LLOUD Official"
  },
  {
    "title": "LISA - ROCKSTAR (Official Music Video)",
    "url": "https://youtube.com/watch?v=hbcGx4MGUMg",
    "duration": 168.0,
    "views": 385677461,
    "uploader": "LLOUD Official"
  },
  {
    "title": "LISA performing Rockstar live from the Victoria’s Secret Fashion Show 2024",
    "url": "https://youtube.com/watch?v=mOLAtBo3mHk",
    "duration": 198.0,
    "views": 39113937,
    "uploader": "LLOUD Official"
  },
  {
    "title": "LISA - BORN AGAIN feat. Doja Cat & RAYE (Official Music Video)",
    "url": "https://youtube.com/watch?v=kbEC-AGr9n0",
    "duration": 245.0,
    "views": 142977498,
    "uploader": "LLOUD Official"
  },
  {
    "title": "LISA - 'LALISA' M/V",
    "url": "https://youtube.com/watch?v=awkkyBH2zEo",
    "duration": 207.0,
    "views": 774618697,
    "uploader": "BLACKPINK"
  },
  {
    "title": "LISA - MOONLIT FLOOR (Official Performance Video)",
    "url": "https://youtube.com/watch?v=pxGM_TOgHuM",
    "duration": 157.0,
    "views": 102591393,
    "uploader": "LLOUD Official"
  },
  {
    "title": "LISA - NEW WOMAN feat. Rosalía (Official Music Video)",
    "url": "https://youtube.com/watch?v=UxXY_hR_wzo",
    "duration": 192.0,
    "views": 195790962,
    "uploader": "LLOUD Official"
  },
  {
    "title": "LISA - FUTW (Vixi Solo Version) (Official Music Video)",
    "url": "https://youtube.com/watch?v=r5VRqWkFpEQ",
    "duration": 228.0,
    "views": 61303523,
    "uploader": "LLOUD Official"
  }
]