[
  {
    "title": "چایی کدوم کشور دنیا بهتره؟",
    "url": "https://youtube.com/watch?v=zPdqkp2UOIo",
    "duration": 1039.0,
    "views": 6282,
    "uploader": "Kouman "
  },
  {
    "title": "بین یوتوبرا محصول کی از همه بهتره؟؟؟",
    "url": "https://youtube.com/watch?v=Kzt4FBi7fCg",
    "duration": 2777.0,
    "views": 1747814,
    "uploader": "Kouman "
  },
  {
    "title": "کدوممون‌ بیشتر اون یکیو دوست داره؟؟؟",
    "url": "https://youtube.com/watch?v=LAzqzXlQ-70",
    "duration": 1031.0,
    "views": 1619401,
    "uploader": "Kouman "
  },
  {
    "title": "هیجان‌انگیز ترین مسابقه کوماندی با میا!!!",
    "url": "https://youtube.com/watch?v=6yZWLV-vT5o",
    "duration": 1872.0,
    "views": 1602882,
    "uploader": "Kouman "
  },
  {
    "title": "آیا این بهترین فست فود دنیاس؟",
    "url": "https://youtube.com/watch?v=RKOV71nx0fE",
    "duration": 1154.0,
    "views": 2141066,
    "uploader": "Kouman "
  },
  {
    "title": "کومان در سفر - رفتیم بهترین رستورانای لس‌آنجلس!!!",
    "url": "https://youtube.com/watch?v=_sc4KTVvxcI",
    "duration": 2199.0,
    "views": 1725651,
    "uploader": "Kouman "
  },
  {
    "title": "عجیب‌ترین چیپس‌های دنیا!",
    "url": "https://youtube.com/watch?v=ZdRSi4puP98",
    "duration": 1235.0,
    "views": 2268217,
    "uploader": "Kouman "
  },
  {
    "title": "بهترین بیسکویت ایرانی کدومه؟",
    "url": "https://youtube.com/watch?v=ae3JMZhWgno",
    "duration": 1345.0,
    "views": 907527,
    "uploader": "Kouman "
  },
  {
    "title": "بازی دروغ‌ها با مجازات!",
    "url": "https://youtube.com/watch?v=H2baO4zSzHE",
    "duration": 989.0,
    "views": 1945910,
    "uploader": "Kouman "
  },
  {
    "title": "ولاگ گرونترین همبرگر",
    "url": "https://youtube.com/watch?v=7s8C5XweKqw",
    "duration": 1181.0,
    "views": 2201424,
    "uploader": "Kouman "
  }
]